echostream_managed_app/__init__.py
echostream_managed_app/__main__.py
echostream_managed_app-0.3.0.dist-info/LICENSE
echostream_managed_app-0.3.0.dist-info/METADATA
echostream_managed_app-0.3.0.dist-info/WHEEL
echostream_managed_app-0.3.0.dist-info/entry_points.txt
echostream_managed_app-0.3.0.dist-info/top_level.txt
echostream_managed_app-0.3.0.dist-info/RECORD
