Metadata-Version: 2.1
Name: echostream-managed-app
Version: 0.3.0
Summary: Application that implements the managed app functionality
License: Proprietary
Classifier: License :: Other/Proprietary License
Classifier: Programming Language :: Python :: 3
Classifier: Programming Language :: Python :: 3.12
Requires-Python: >=3.12
License-File: LICENSE
Requires-Dist: aiorun ==2024.5.1
Requires-Dist: aws-error-utils ==2.7.0
Requires-Dist: awsserviceendpoints ==0.0.2
Requires-Dist: backoff ==2.2.1
Requires-Dist: boto3 ==1.34.144
Requires-Dist: docker ==7.1.0
Requires-Dist: echostream-node ==0.4.1
Requires-Dist: gql[aiohttp] ==3.5.0
Requires-Dist: gql-appsync-cognito-authentication ==0.0.1
Requires-Dist: pycognito ==2024.5.1
Requires-Dist: python-dateutil ==2.9.0.post0
Requires-Dist: sdnotify ==0.3.2
Requires-Dist: simplejson ==3.19.2
Requires-Dist: uvloop ==0.19.0
Requires-Dist: watchtower ==3.2.0
